proy3/__init__.py
proy3-0.0.2.dist-info/LICENSE.txt
proy3-0.0.2.dist-info/METADATA
proy3-0.0.2.dist-info/WHEEL
proy3-0.0.2.dist-info/top_level.txt
proy3-0.0.2.dist-info/RECORD
